candlelight/__init__.py
candlelight/constants.py
candlelight/helpers.py
candlelight/networks/__init__.py
candlelight/nlp/__init__.py
candlelight/nlp/embedding/README.md
candlelight/nlp/embedding/__init__.py
candlelight/nlp/embedding/embedding.py
candlelight/nlp/embedding/model.py
candlelight/nlp/embedding/models.py
candlelight/nlp/embedding/sbert.py
candlelight/spatial/__init__.py
candlelight/spatial/common.py
candlelight/spatial/convert_pose.py
candlelight/spatial/convert_rotation.py
candlelight/spatial/entity.py
candlelight/spatial/euler_angles.py
candlelight/spatial/pose.py
candlelight/spatial/quaternion.py
candlelight/spatial/rotation.py
candlelight/spatial/twist.py
candlelight/spatial/vector.py
candlelight/types_alias.py
candlelight/vision/__init__.py
candlelight/vision/batch.py
candlelight/vision/image.py
candlelight-0.0.1.dist-info/METADATA
candlelight-0.0.1.dist-info/WHEEL
candlelight-0.0.1.dist-info/RECORD
