Metadata-Version: 2.1
Name: candlelight
Version: 0.0.1
Summary: 
Author: Thibaut DEVERAUX
Author-email: thibaut.deveraux@gmail.com
Requires-Python: >=3.10,<3.12
Classifier: Programming Language :: Python :: 3
Classifier: Programming Language :: Python :: 3.10
Classifier: Programming Language :: Python :: 3.11
Requires-Dist: nptyping (>=2.5.0,<3.0.0)
Requires-Dist: numpy (>=1.24,<2.0)
Requires-Dist: pytorch-lightning (>=1.9.4,<2.0.0)
Requires-Dist: scipy (>=1.10.1,<2.0.0)
Requires-Dist: sentence-transformers (>=2.2.2,<3.0.0)
Requires-Dist: torch (>=1.13.1,<2.0.0)
Requires-Dist: torchvision (>=0.14.1,<0.15.0)
